timeseries_modeling/__init__.py
timeseries_modeling/assessor.py
timeseries_modeling/dataframes/__init__.py
timeseries_modeling/dataframes/csvdataframe.py
timeseries_modeling/dataframes/quandldataframe.py
timeseries_modeling/dataframes/ticketdataframe.py
timeseries_modeling/predictors/__init__.py
timeseries_modeling/predictors/arima.py
timeseries_modeling/predictors/autoregression/__init__.py
timeseries_modeling/predictors/autoregression/v1.py
timeseries_modeling/predictors/autoregression/v2.py
timeseries_modeling/predictors/autoregression/var.py
timeseries_modeling/predictors/decomposition/__init__.py
timeseries_modeling/predictors/decomposition/decompositions.py
timeseries_modeling/predictors/garch.py
timeseries_modeling/predictors/hannenriessen.py
timeseries_modeling/predictors/montecarlo.py
timeseries_modeling/predictors/naive.py
timeseries_modeling/smoothers.py
timeseries_modeling/utils.py
timeseries_modeling-0.1.1.dist-info/LICENSE.md
timeseries_modeling-0.1.1.dist-info/WHEEL
timeseries_modeling-0.1.1.dist-info/METADATA
timeseries_modeling-0.1.1.dist-info/RECORD
