Metadata-Version: 2.1
Name: timeseries-modeling
Version: 0.1.1
Summary: Package to handle time series data, make predictions, and assess them
License: MIT
Author: David Rodriguez
Author-email: davidrp1996@gmail.com
Requires-Python: >=3.7,<4.0
Classifier: License :: OSI Approved :: MIT License
Classifier: Programming Language :: Python :: 3
Classifier: Programming Language :: Python :: 3.7
Classifier: Programming Language :: Python :: 3.8
Classifier: Programming Language :: Python :: 3.9
Classifier: Programming Language :: Python :: 3.10
Requires-Dist: Quandl (>=3.7.0,<4.0.0)
Requires-Dist: matplotlib (>=3.6.0,<4.0.0)
Requires-Dist: numpy (>=1.23.3,<2.0.0)
Requires-Dist: pandas (>=1.4.4,<2.0.0)
Requires-Dist: statsmodels (>=0.13.2,<0.14.0)
Requires-Dist: yfinance (>=0.1.74,<0.2.0)
